GeoScraper/__init__.py
GeoScraper-0.0.1.dist-info/LICENSE
GeoScraper-0.0.1.dist-info/METADATA
GeoScraper-0.0.1.dist-info/WHEEL
GeoScraper-0.0.1.dist-info/top_level.txt
GeoScraper-0.0.1.dist-info/RECORD
