Metadata-Version: 2.1
Name: GeoScraper
Version: 0.0.1
Summary: Very user friendly library to parse OpenSourceMap data either from an XML file (i.e. *.osm), from an OSM API URL, or from a user specified bounding box
Home-page: https://github.com/PowerBroker2/GeoScraper
Download-URL: https://github.com/PowerBroker2/GeoScraper/archive/0.0.1.tar.gz
Author: Power_Broker
Author-email: gitstuff2@gmail.com
Keywords: geospacial,map,maps,mapping,osm,openstreetmap
License-File: LICENSE
Requires-Dist: xmltodict
Requires-Dist: simplekml
